coinblockpro/__init__.py
coinblockpro-0.0.2.data/scripts/rest_server.py
coinblockpro-0.0.2.data/scripts/run_cbp_server
coinblockpro-0.0.2.data/scripts/ws_server.py
coinblockpro-0.0.2.dist-info/LICENSE
coinblockpro-0.0.2.dist-info/METADATA
coinblockpro-0.0.2.dist-info/WHEEL
coinblockpro-0.0.2.dist-info/top_level.txt
coinblockpro-0.0.2.dist-info/RECORD
