Metadata-Version: 2.1
Name: coinblockpro
Version: 0.0.2
Summary: A toy server written in Sanic to mimic an online currency exchange, with a REST and websocket API.
Home-page: https://github.com/hypernormalisation/coinblockpro
Author: Stephen Ogilvy
Author-email: sogilvy@tuta.io
License: UNKNOWN
Project-URL: Source, https://github.com/hypernormalisation/coinblockpro
Keywords: logging
Platform: UNKNOWN
Classifier: Development Status :: 3 - Alpha
Classifier: Intended Audience :: Developers
Classifier: License :: OSI Approved :: GNU General Public License v3 or later (GPLv3+)
Classifier: Programming Language :: Python :: 3
Classifier: Programming Language :: Python :: 3.6
Classifier: Programming Language :: Python :: 3.7
Classifier: Programming Language :: Python :: 3.8
Requires-Python: >=3.6
Requires-Dist: sanic
Requires-Dist: dataset
Requires-Dist: websockets
Requires-Dist: requests
